demazon/__init__.py
demazon/main.py
demazon/codes/1.txt
demazon-0.0.2.dist-info/METADATA
demazon-0.0.2.dist-info/WHEEL
demazon-0.0.2.dist-info/top_level.txt
demazon-0.0.2.dist-info/RECORD
