Metadata-Version: 2.4
Name: demazon
Version: 0.0.2
Summary: A Python package that retrieves code snippets by number
Author: demazon
License: MIT
